mlep/__init__.py
mlep/mlep_create.py
mlep/mlep_decode_packet.py
mlep/mlep_encode_real_data.py
mlep/mlep_encode_status.py
mlep/mlep_error.py
mlep/mlep_parse_json.py
mlep/mlep_process.py
mlep-0.1.dev2.dist-info/LICENSE.txt
mlep-0.1.dev2.dist-info/METADATA
mlep-0.1.dev2.dist-info/WHEEL
mlep-0.1.dev2.dist-info/top_level.txt
mlep-0.1.dev2.dist-info/RECORD
