Metadata-Version: 2.1
Name: mlep
Version: 0.1.dev2
Summary: Interact with an EnergyPlus simulation during runtime using the BCVTB protocol.
Home-page: https://github.com/corymosiman12/python-mlep
Author: Cory Mosiman
Author-email: UNKNOWN
License: MIT
Platform: UNKNOWN
